<?xml version="1.0" encoding="utf-8" ?>
<dwsync>
<file name="13.png" server="104.238.146.116" local="132611838010000000" remote="132611838010000000" Dst="0" />
<file name="20.png" server="104.238.146.116" local="132611838120000000" remote="132611838120000000" Dst="0" />
<file name="3.png" server="104.238.146.116" local="132611838130000000" remote="132611838130000000" Dst="0" />
<file name="7.png" server="104.238.146.116" local="132611838180000000" remote="132611838180000000" Dst="0" />
<file name="12.png" server="104.238.146.116" local="132611837990000000" remote="132611837990000000" Dst="0" />
<file name="15.png" server="104.238.146.116" local="132611838030000000" remote="132611838030000000" Dst="0" />
<file name="14.png" server="104.238.146.116" local="132611838020000000" remote="132611838020000000" Dst="0" />
<file name="8.png" server="104.238.146.116" local="132611838190000000" remote="132611838190000000" Dst="0" />
<file name="19.png" server="104.238.146.116" local="132611838090000000" remote="132611838090000000" Dst="0" />
<file name="1.png" server="104.238.146.116" local="132611837950000000" remote="132611837950000000" Dst="0" />
<file name="4.png" server="104.238.146.116" local="132611838140000000" remote="132611838140000000" Dst="0" />
<file name="5.png" server="104.238.146.116" local="132611838150000000" remote="132611838150000000" Dst="0" />
<file name="9.png" server="104.238.146.116" local="132611838210000000" remote="132611838210000000" Dst="0" />
<file name="11.png" server="104.238.146.116" local="132611837980000000" remote="132611837980000000" Dst="0" />
<file name="2.png" server="104.238.146.116" local="132611838100000000" remote="132611838100000000" Dst="0" />
<file name="17.png" server="104.238.146.116" local="132611838060000000" remote="132611838060000000" Dst="0" />
<file name="16.png" server="104.238.146.116" local="132611838050000000" remote="132611838050000000" Dst="0" />
<file name="6.png" server="104.238.146.116" local="132611838170000000" remote="132611838170000000" Dst="0" />
<file name="18.png" server="104.238.146.116" local="132611838080000000" remote="132611838080000000" Dst="0" />
<file name="10.png" server="104.238.146.116" local="132611837970000000" remote="132611837970000000" Dst="0" />
</dwsync>